{"result": [{"contestId": 16,"contestName": "Codeforces Beta Round #16 (Div. 2 Only)","handle": "coquelicot","newRating": 1604,"oldRating": 1500,"rank": 43,"ratingUpdateTimeSeconds": 1275577200},{"contestId": 214,"contestName": "Codeforces Round #131 (Div. 2)","handle": "coquelicot","newRating": 1662,"oldRating": 1604,"rank": 129,"ratingUpdateTimeSeconds": 1343669400},{"contestId": 230,"contestName": "Codeforces Round #142 (Div. 2)","handle": "coquelicot","newRating": 1767,"oldRating": 1662,"rank": 1,"ratingUpdateTimeSeconds": 1349112900},{"contestId": 243,"contestName": "Codeforces Round #150 (Div. 1)","handle": "coquelicot","newRating": 1710,"oldRating": 1767,"rank": 298,"ratingUpdateTimeSeconds": 1353087600},{"contestId": 274,"contestName": "Codeforces Round #168 (Div. 1)","handle": "coquelicot","newRating": 1794,"oldRating": 1710,"rank": 198,"ratingUpdateTimeSeconds": 1361381400},{"contestId": 283,"contestName": "Codeforces Round #174 (Div. 1)","handle": "coquelicot","newRating": 1860,"oldRating": 1794,"rank": 218,"ratingUpdateTimeSeconds": 1363541700},{"contestId": 286,"contestName": "Codeforces Round #176 (Div. 1)","handle": "coquelicot","newRating": 1856,"oldRating": 1860,"rank": 238,"ratingUpdateTimeSeconds": 1364032800},{"contestId": 331,"contestName": "ABBYY Cup 3.0 - Finals (online version)","handle": "coquelicot","newRating": 1983,"oldRating": 1856,"rank": 35,"ratingUpdateTimeSeconds": 1374083100}],"status": "OK"}