{"result": [{"contestId": 215,"contestName": "Codeforces Round #132 (Div. 2)","handle": "Dr.","newRating": 1509,"oldRating": 1500,"rank": 532,"ratingUpdateTimeSeconds": 1344274200},{"contestId": 218,"contestName": "Codeforces Round #134 (Div. 2)","handle": "Dr.","newRating": 1608,"oldRating": 1509,"rank": 152,"ratingUpdateTimeSeconds": 1345280700},{"contestId": 219,"contestName": "Codeforces Round #135 (Div. 2)","handle": "Dr.","newRating": 1700,"oldRating": 1608,"rank": 82,"ratingUpdateTimeSeconds": 1346088600},{"contestId": 220,"contestName": "Codeforces Round #136 (Div. 1)","handle": "Dr.","newRating": 1733,"oldRating": 1700,"rank": 249,"ratingUpdateTimeSeconds": 1346434200},{"contestId": 229,"contestName": "Codeforces Round #142 (Div. 1)","handle": "Dr.","newRating": 1671,"oldRating": 1733,"rank": 399,"ratingUpdateTimeSeconds": 1349112900},{"contestId": 231,"contestName": "Codeforces Round #143 (Div. 2)","handle": "Dr.","newRating": 1668,"oldRating": 1671,"rank": 202,"ratingUpdateTimeSeconds": 1349631000},{"contestId": 236,"contestName": "Codeforces Round #146 (Div. 2)","handle": "Dr.","newRating": 1681,"oldRating": 1668,"rank": 151,"ratingUpdateTimeSeconds": 1350810600},{"contestId": 237,"contestName": "Codeforces Round #147 (Div. 2)","handle": "Dr.","newRating": 1699,"oldRating": 1681,"rank": 160,"ratingUpdateTimeSeconds": 1351186200},{"contestId": 239,"contestName": "Codeforces Round #148 (Div. 2)","handle": "Dr.","newRating": 1616,"oldRating": 1699,"rank": 522,"ratingUpdateTimeSeconds": 1352052000},{"contestId": 320,"contestName": "Codeforces Round #189 (Div. 2)","handle": "Dr.","newRating": 1702,"oldRating": 1616,"rank": 84,"ratingUpdateTimeSeconds": 1372000200},{"contestId": 329,"contestName": "Codeforces Round #192 (Div. 1)","handle": "Dr.","newRating": 1675,"oldRating": 1702,"rank": 394,"ratingUpdateTimeSeconds": 1374334200},{"contestId": 334,"contestName": "Codeforces Round #194 (Div. 2)","handle": "Dr.","newRating": 1585,"oldRating": 1675,"rank": 1299,"ratingUpdateTimeSeconds": 1374921000},{"contestId": 344,"contestName": "Codeforces Round #200 (Div. 2)","handle": "Dr.","newRating": 1522,"oldRating": 1585,"rank": 637,"ratingUpdateTimeSeconds": 1379180400},{"contestId": 373,"contestName": "Codeforces Round #219 (Div. 2)","handle": "Dr.","newRating": 1661,"oldRating": 1522,"rank": 107,"ratingUpdateTimeSeconds": 1386950400},{"contestId": 416,"contestName": "Codeforces Round #241 (Div. 2)","handle": "Dr.","newRating": 1734,"oldRating": 1661,"rank": 53,"ratingUpdateTimeSeconds": 1397383200},{"contestId": 438,"contestName": "Codeforces Round #250 (Div. 1)","handle": "Dr.","newRating": 1842,"oldRating": 1734,"rank": 227,"ratingUpdateTimeSeconds": 1401634800},{"contestId": 477,"contestName": "Codeforces Round #272 (Div. 1)","handle": "Dr.","newRating": 1788,"oldRating": 1842,"rank": 569,"ratingUpdateTimeSeconds": 1413129600},{"contestId": 549,"contestName": "Looksery Cup 2015","handle": "Dr.","newRating": 1769,"oldRating": 1788,"rank": 1244,"ratingUpdateTimeSeconds": 1433604600},{"contestId": 555,"contestName": "Codeforces Round #310 (Div. 1)","handle": "Dr.","newRating": 1992,"oldRating": 1769,"rank": 155,"ratingUpdateTimeSeconds": 1435421400}],"status": "OK"}