{"result": [{"contestId": 729,"contestName": "Technocup 2017 - Elimination Round 2","handle": "dubrovin","newRating": 1441,"oldRating": 1500,"rank": 623,"ratingUpdateTimeSeconds": 1479639900},{"contestId": 740,"contestName": "Codeforces Round #381 (Div. 2)","handle": "dubrovin","newRating": 1438,"oldRating": 1441,"rank": 1623,"ratingUpdateTimeSeconds": 1479926100},{"contestId": 735,"contestName": "Codeforces Round #382 (Div. 2)","handle": "dubrovin","newRating": 1337,"oldRating": 1438,"rank": 3539,"ratingUpdateTimeSeconds": 1480271700},{"contestId": 742,"contestName": "Codeforces Round #383 (Div. 2)","handle": "dubrovin","newRating": 1291,"oldRating": 1337,"rank": 3191,"ratingUpdateTimeSeconds": 1481042100},{"contestId": 745,"contestName": "Codeforces Round #385 (Div. 2)","handle": "dubrovin","newRating": 1183,"oldRating": 1291,"rank": 3784,"ratingUpdateTimeSeconds": 1481999700},{"contestId": 748,"contestName": "Technocup 2017 - Elimination Round 3","handle": "dubrovin","newRating": 1235,"oldRating": 1183,"rank": 405,"ratingUpdateTimeSeconds": 1482663900},{"contestId": 779,"contestName": "Codeforces Round #402 (Div. 2)","handle": "dubrovin","newRating": 1234,"oldRating": 1235,"rank": 1992,"ratingUpdateTimeSeconds": 1488103500},{"contestId": 782,"contestName": "Codeforces Round #403 (Div. 2, based on Technocup 2017 Finals)","handle": "dubrovin","newRating": 1163,"oldRating": 1234,"rank": 3116,"ratingUpdateTimeSeconds": 1488726300},{"contestId": 785,"contestName": "Codeforces Round #404 (Div. 2)","handle": "dubrovin","newRating": 1082,"oldRating": 1163,"rank": 4532,"ratingUpdateTimeSeconds": 1489598100},{"contestId": 793,"contestName": "Tinkoff Challenge - Elimination Round","handle": "dubrovin","newRating": 1124,"oldRating": 1082,"rank": 2005,"ratingUpdateTimeSeconds": 1492973100},{"contestId": 812,"contestName": "Codeforces Round #417 (Div. 2)","handle": "dubrovin","newRating": 1166,"oldRating": 1124,"rank": 2252,"ratingUpdateTimeSeconds": 1496333700},{"contestId": 851,"contestName": "Codeforces Round #432 (Div. 2, based on IndiaHacks Final Round 2017)","handle": "dubrovin","newRating": 1217,"oldRating": 1166,"rank": 2065,"ratingUpdateTimeSeconds": 1504544700},{"contestId": 904,"contestName": "ÑSÑuÑáÑ~ÑÄÑ{ÑÖÑqÑÄÑ{ 2018 - ÑOÑÑÑqÑÄÑÇÑÄÑâÑ~ÑçÑz ÑQÑpÑÖÑ~Ñt 4","handle": "dubrovin","newRating": 1528,"oldRating": 1217,"rank": 14,"ratingUpdateTimeSeconds": 1514045100},{"contestId": 944,"contestName": "ÑSÑuÑáÑ~ÑÄÑ{ÑÖÑqÑÄÑ{ 2018 - ÑUÑyÑ~ÑpÑ| (ÑÑÑÄÑ|ÑéÑ{ÑÄ ÑtÑ|Ñë ÑÄÑ~ÑÉÑpÑzÑÑ-ÑÜÑyÑ~ÑpÑ|ÑyÑÉÑÑÑÄÑr)","handle": "dubrovin","newRating": 1551,"oldRating": 1528,"rank": 170,"ratingUpdateTimeSeconds": 1520163600},{"contestId": 954,"contestName": "Educational Codeforces Round 40 (Rated for Div. 2)","handle": "dubrovin","newRating": 1626,"oldRating": 1551,"rank": 247,"ratingUpdateTimeSeconds": 1521709500},{"contestId": 1025,"contestName": "Codeforces Round #505 (rated, Div. 1 + Div. 2, based on VK Cup 2018 Final)","handle": "dubrovin","newRating": 1567,"oldRating": 1626,"rank": 2934,"ratingUpdateTimeSeconds": 1534693800},{"contestId": 1029,"contestName": "Codeforces Round #506 (Div. 3)","handle": "dubrovin","newRating": 1542,"oldRating": 1567,"rank": 1419,"ratingUpdateTimeSeconds": 1535129400},{"contestId": 1028,"contestName": "AIM Tech Round 5 (rated, Div. 1 + Div. 2)","handle": "dubrovin","newRating": 1518,"oldRating": 1542,"rank": 2073,"ratingUpdateTimeSeconds": 1535395800},{"contestId": 1030,"contestName": "Technocup 2019 - Elimination Round 1","handle": "dubrovin","newRating": 1539,"oldRating": 1518,"rank": 527,"ratingUpdateTimeSeconds": 1537715100},{"contestId": 1065,"contestName": "Educational Codeforces Round 52 (Rated for Div. 2)","handle": "dubrovin","newRating": 1622,"oldRating": 1539,"rank": 576,"ratingUpdateTimeSeconds": 1539276600},{"contestId": 1031,"contestName": "Technocup 2019 - Elimination Round 2","handle": "dubrovin","newRating": 1762,"oldRating": 1622,"rank": 29,"ratingUpdateTimeSeconds": 1540116600},{"contestId": 1091,"contestName": "Good Bye 2018","handle": "dubrovin","newRating": 1750,"oldRating": 1762,"rank": 2052,"ratingUpdateTimeSeconds": 1546190100},{"contestId": 1113,"contestName": "Codeforces Round #539 (Div. 2)","handle": "dubrovin","newRating": 1732,"oldRating": 1750,"rank": 864,"ratingUpdateTimeSeconds": 1550343900},{"contestId": 1112,"contestName": "Technocup 2019 - Final","handle": "dubrovin","newRating": 1778,"oldRating": 1732,"rank": 143,"ratingUpdateTimeSeconds": 1551612600},{"contestId": 1143,"contestName": "Codeforces Round #549 (Div. 2)","handle": "dubrovin","newRating": 1776,"oldRating": 1778,"rank": 518,"ratingUpdateTimeSeconds": 1553973000},{"contestId": 1182,"contestName": "Codeforces Round #566 (Div. 2)","handle": "dubrovin","newRating": 1770,"oldRating": 1776,"rank": 909,"ratingUpdateTimeSeconds": 1560265500},{"contestId": 1200,"contestName": "Codeforces Round #578 (Div. 2)","handle": "dubrovin","newRating": 1877,"oldRating": 1770,"rank": 194,"ratingUpdateTimeSeconds": 1565534100},{"contestId": 1206,"contestName": "Codeforces Round #580 (Div. 2)","handle": "dubrovin","newRating": 1828,"oldRating": 1877,"rank": 1220,"ratingUpdateTimeSeconds": 1566143700},{"contestId": 1204,"contestName": "Codeforces Round #581 (Div. 2)","handle": "dubrovin","newRating": 1884,"oldRating": 1828,"rank": 395,"ratingUpdateTimeSeconds": 1566318900},{"contestId": 1208,"contestName": "Manthan, Codefest 19 (open for everyone, rated, Div. 1 + Div. 2)","handle": "dubrovin","newRating": 1918,"oldRating": 1884,"rank": 726,"ratingUpdateTimeSeconds": 1566751200},{"contestId": 1215,"contestName": "Codeforces Round #585 (Div. 2)","handle": "dubrovin","newRating": 1898,"oldRating": 1918,"rank": 663,"ratingUpdateTimeSeconds": 1568550900},{"contestId": 1220,"contestName": "Codeforces Round #586 (Div. 1 + Div. 2)","handle": "dubrovin","newRating": 1933,"oldRating": 1898,"rank": 539,"ratingUpdateTimeSeconds": 1568829900},{"contestId": 1221,"contestName": "Educational Codeforces Round 73 (Rated for Div. 2)","handle": "dubrovin","newRating": 2003,"oldRating": 1933,"rank": 121,"ratingUpdateTimeSeconds": 1568910900},{"contestId": 1228,"contestName": "Codeforces Round #589 (Div. 2)","handle": "dubrovin","newRating": 2042,"oldRating": 2003,"rank": 216,"ratingUpdateTimeSeconds": 1569769500},{"contestId": 1238,"contestName": "Educational Codeforces Round 74 (Rated for Div. 2)","handle": "dubrovin","newRating": 1999,"oldRating": 2042,"rank": 665,"ratingUpdateTimeSeconds": 1570553700},{"contestId": 1236,"contestName": "Codeforces Round #593 (Div. 2)","handle": "dubrovin","newRating": 2090,"oldRating": 1999,"rank": 67,"ratingUpdateTimeSeconds": 1571326500},{"contestId": 1251,"contestName": "Educational Codeforces Round 75 (Rated for Div. 2)","handle": "dubrovin","newRating": 2026,"oldRating": 2090,"rank": 724,"ratingUpdateTimeSeconds": 1571936700}],"status": "OK"}