{"result": [{"contestId": 897,"contestName": "Codeforces Round #449 (Div. 2)","handle": "Furukawa-Nagisa","newRating": 1534,"oldRating": 1500,"rank": 546,"ratingUpdateTimeSeconds": 1512231600},{"contestId": 908,"contestName": "Good Bye 2017","handle": "Furukawa-Nagisa","newRating": 1537,"oldRating": 1534,"rank": 2542,"ratingUpdateTimeSeconds": 1514571000},{"contestId": 932,"contestName": "ICM Technex 2018 and Codeforces Round #463 (Div. 1 + Div. 2, combined)","handle": "Furukawa-Nagisa","newRating": 1787,"oldRating": 1537,"rank": 117,"ratingUpdateTimeSeconds": 1518712500},{"contestId": 939,"contestName": "Codeforces Round #464 (Div. 2)","handle": "Furukawa-Nagisa","newRating": 2001,"oldRating": 1787,"rank": 6,"ratingUpdateTimeSeconds": 1518869100},{"contestId": 1091,"contestName": "Good Bye 2018","handle": "Furukawa-Nagisa","newRating": 2116,"oldRating": 2001,"rank": 226,"ratingUpdateTimeSeconds": 1546190100},{"contestId": 1097,"contestName": "Hello 2019","handle": "Furukawa-Nagisa","newRating": 2150,"oldRating": 2116,"rank": 363,"ratingUpdateTimeSeconds": 1546623900},{"contestId": 1110,"contestName": "Codeforces Global Round 1","handle": "Furukawa-Nagisa","newRating": 2255,"oldRating": 2150,"rank": 129,"ratingUpdateTimeSeconds": 1549553700},{"contestId": 1119,"contestName": "Codeforces Global Round 2","handle": "Furukawa-Nagisa","newRating": 2167,"oldRating": 2255,"rank": 953,"ratingUpdateTimeSeconds": 1554557700},{"contestId": 1158,"contestName": "Codeforces Round #559 (Div. 1)","handle": "Furukawa-Nagisa","newRating": 2173,"oldRating": 2167,"rank": 176,"ratingUpdateTimeSeconds": 1557678900},{"contestId": 1148,"contestName": "Codeforces Global Round 3","handle": "Furukawa-Nagisa","newRating": 2177,"oldRating": 2173,"rank": 369,"ratingUpdateTimeSeconds": 1559407800},{"contestId": 1172,"contestName": "Codeforces Round #564 (Div. 1)","handle": "Furukawa-Nagisa","newRating": 2217,"oldRating": 2177,"rank": 152,"ratingUpdateTimeSeconds": 1559916300},{"contestId": 1188,"contestName": "Codeforces Round #572 (Div. 1)","handle": "Furukawa-Nagisa","newRating": 2143,"oldRating": 2217,"rank": 396,"ratingUpdateTimeSeconds": 1562346300},{"contestId": 1190,"contestName": "Codeforces Round #573 (Div. 1)","handle": "Furukawa-Nagisa","newRating": 2069,"oldRating": 2143,"rank": 541,"ratingUpdateTimeSeconds": 1562949300},{"contestId": 1178,"contestName": "Codeforces Global Round 4","handle": "Furukawa-Nagisa","newRating": 2096,"oldRating": 2069,"rank": 386,"ratingUpdateTimeSeconds": 1563645900},{"contestId": 1237,"contestName": "Codeforces Global Round 5","handle": "Furukawa-Nagisa","newRating": 2171,"oldRating": 2096,"rank": 257,"ratingUpdateTimeSeconds": 1571245500},{"contestId": 1242,"contestName": "Codeforces Round #599 (Div. 1)","handle": "Furukawa-Nagisa","newRating": 2198,"oldRating": 2171,"rank": 250,"ratingUpdateTimeSeconds": 1573059900}],"status": "OK"}