{"result": [{"contestId": 339,"contestName": "Codeforces Round #197 (Div. 2)","handle": "KybRonnoc","newRating": 1756,"oldRating": 1500,"rank": 7,"ratingUpdateTimeSeconds": 1377538200},{"contestId": 633,"contestName": "Manthan, Codefest 16","handle": "KybRonnoc","newRating": 1840,"oldRating": 1756,"rank": 284,"ratingUpdateTimeSeconds": 1456515900},{"contestId": 635,"contestName": "8VC Venture Cup 2016 - Final Round (Div. 2 Edition)","handle": "KybRonnoc","newRating": 1860,"oldRating": 1840,"rank": 133,"ratingUpdateTimeSeconds": 1456690200},{"contestId": 653,"contestName": "IndiaHacks 2016 - Online Edition (Div. 1 + Div. 2)","handle": "KybRonnoc","newRating": 1936,"oldRating": 1860,"rank": 198,"ratingUpdateTimeSeconds": 1458383700}],"status": "OK"}