{"result": [{"contestId": 583,"contestName": "Codeforces Round #323 (Div. 2)","handle": "lchacon","newRating": 1590,"oldRating": 1500,"rank": 240,"ratingUpdateTimeSeconds": 1443897900},{"contestId": 584,"contestName": "Codeforces Round #324 (Div. 2)","handle": "lchacon","newRating": 1702,"oldRating": 1590,"rank": 59,"ratingUpdateTimeSeconds": 1444156200},{"contestId": 592,"contestName": "Codeforces Round #328 (Div. 2)","handle": "lchacon","newRating": 1902,"oldRating": 1702,"rank": 17,"ratingUpdateTimeSeconds": 1446316200},{"contestId": 605,"contestName": "Codeforces Round #335 (Div. 1)","handle": "lchacon","newRating": 1830,"oldRating": 1902,"rank": 398,"ratingUpdateTimeSeconds": 1449684300},{"contestId": 629,"contestName": "Codeforces Round #343 (Div. 2)","handle": "lchacon","newRating": 1875,"oldRating": 1830,"rank": 134,"ratingUpdateTimeSeconds": 1455993300},{"contestId": 705,"contestName": "Codeforces Round #366 (Div. 2)","handle": "lchacon","newRating": 1869,"oldRating": 1875,"rank": 386,"ratingUpdateTimeSeconds": 1470585900},{"contestId": 742,"contestName": "Codeforces Round #383 (Div. 2)","handle": "lchacon","newRating": 1923,"oldRating": 1869,"rank": 124,"ratingUpdateTimeSeconds": 1481042100},{"contestId": 763,"contestName": "Codeforces Round #395 (Div. 1)","handle": "lchacon","newRating": 1978,"oldRating": 1923,"rank": 243,"ratingUpdateTimeSeconds": 1486049700},{"contestId": 790,"contestName": "Codeforces Round #405 (rated, Div. 1, based on VK Cup 2017 Round 1)","handle": "lchacon","newRating": 1926,"oldRating": 1978,"rank": 346,"ratingUpdateTimeSeconds": 1489858500},{"contestId": 815,"contestName": "Codeforces Round #419 (Div. 1)","handle": "lchacon","newRating": 2013,"oldRating": 1926,"rank": 200,"ratingUpdateTimeSeconds": 1497717300},{"contestId": 833,"contestName": "Codeforces Round #426 (Div. 1)","handle": "lchacon","newRating": 1924,"oldRating": 2013,"rank": 380,"ratingUpdateTimeSeconds": 1501432500},{"contestId": 840,"contestName": "Codeforces Round #429 (Div. 1)","handle": "lchacon","newRating": 1890,"oldRating": 1924,"rank": 409,"ratingUpdateTimeSeconds": 1503075900},{"contestId": 854,"contestName": "Codeforces Round #433 (Div. 2, based on Olympiad of Metropolises)","handle": "lchacon","newRating": 1953,"oldRating": 1890,"rank": 81,"ratingUpdateTimeSeconds": 1504709700},{"contestId": 859,"contestName": "MemSQL Start[c]UP 3.0 - Round 1","handle": "lchacon","newRating": 2063,"oldRating": 1953,"rank": 131,"ratingUpdateTimeSeconds": 1505592300},{"contestId": 908,"contestName": "Good Bye 2017","handle": "lchacon","newRating": 2020,"oldRating": 2063,"rank": 1017,"ratingUpdateTimeSeconds": 1514571000},{"contestId": 913,"contestName": "Hello 2018","handle": "lchacon","newRating": 2044,"oldRating": 2020,"rank": 453,"ratingUpdateTimeSeconds": 1515431700},{"contestId": 933,"contestName": "Codeforces Round #462 (Div. 1)","handle": "lchacon","newRating": 2101,"oldRating": 2044,"rank": 146,"ratingUpdateTimeSeconds": 1518617100},{"contestId": 936,"contestName": "Codeforces Round #467 (Div. 1)","handle": "lchacon","newRating": 2051,"oldRating": 2101,"rank": 309,"ratingUpdateTimeSeconds": 1519581900},{"contestId": 983,"contestName": "Codeforces Round #483 (Div. 1) [Thanks, Botan Investments and Victor Shaburov!]","handle": "lchacon","newRating": 2051,"oldRating": 2051,"rank": 270,"ratingUpdateTimeSeconds": 1526402700},{"contestId": 991,"contestName": "Codeforces Round #491 (Div. 2)","handle": "lchacon","newRating": 1997,"oldRating": 2051,"rank": 565,"ratingUpdateTimeSeconds": 1529775300},{"contestId": 1023,"contestName": "Codeforces Round #504 (rated, Div. 1 + Div. 2, based on VK Cup 2018 Final)","handle": "lchacon","newRating": 2054,"oldRating": 1997,"rank": 272,"ratingUpdateTimeSeconds": 1534524600},{"contestId": 1025,"contestName": "Codeforces Round #505 (rated, Div. 1 + Div. 2, based on VK Cup 2018 Final)","handle": "lchacon","newRating": 2051,"oldRating": 2054,"rank": 528,"ratingUpdateTimeSeconds": 1534693800}],"status": "OK"}