{"result": [{"contestId": 1006,"contestName": "Codeforces Round #498 (Div. 3)","handle": "LittleFairyKiki","newRating": 1716,"oldRating": 1500,"rank": 16,"ratingUpdateTimeSeconds": 1531758900},{"contestId": 1013,"contestName": "Codeforces Round #500 (Div. 2) [based on EJOI]","handle": "LittleFairyKiki","newRating": 1913,"oldRating": 1716,"rank": 14,"ratingUpdateTimeSeconds": 1532947500},{"contestId": 1080,"contestName": "Codeforces Round #524 (Div. 2)","handle": "LittleFairyKiki","newRating": 1985,"oldRating": 1913,"rank": 93,"ratingUpdateTimeSeconds": 1543053000}],"status": "OK"}