{"result": [{"contestId": 839,"contestName": "Codeforces Round #428 (Div. 2)","handle": "Mizuno_Akane","newRating": 1570,"oldRating": 1500,"rank": 673,"ratingUpdateTimeSeconds": 1502555700},{"contestId": 877,"contestName": "Codeforces Round #442 (Div. 2)","handle": "Mizuno_Akane","newRating": 1750,"oldRating": 1570,"rank": 67,"ratingUpdateTimeSeconds": 1508780700},{"contestId": 894,"contestName": "Codeforces Round #447 (Div. 2)","handle": "Mizuno_Akane","newRating": 1864,"oldRating": 1750,"rank": 65,"ratingUpdateTimeSeconds": 1511106900},{"contestId": 893,"contestName": "Educational Codeforces Round 33 (Rated for Div. 2)","handle": "Mizuno_Akane","newRating": 2094,"oldRating": 1864,"rank": 2,"ratingUpdateTimeSeconds": 1511456700}],"status": "OK"}