{"result": [{"contestId": 37,"contestName": "Codeforces Beta Round #37","handle": "nab","newRating": 1588,"oldRating": 1500,"rank": 364,"ratingUpdateTimeSeconds": 1288026000},{"contestId": 38,"contestName": "School Personal Contest #1 (Winter Computer School 2010/11) - Codeforces Beta Round #38 (ACM-ICPC Rules)","handle": "nab","newRating": 1453,"oldRating": 1588,"rank": 0,"ratingUpdateTimeSeconds": 1288454400},{"contestId": 40,"contestName": "Codeforces Beta Round #39","handle": "nab","newRating": 1389,"oldRating": 1453,"rank": 410,"ratingUpdateTimeSeconds": 1288980000},{"contestId": 41,"contestName": "Codeforces Beta Round #40 (Div. 2)","handle": "nab","newRating": 1585,"oldRating": 1389,"rank": 18,"ratingUpdateTimeSeconds": 1289239200},{"contestId": 46,"contestName": "School Personal Contest #2 (Winter Computer School 2010/11) - Codeforces Beta Round #43 (ACM-ICPC Rules)","handle": "nab","newRating": 1662,"oldRating": 1585,"rank": 191,"ratingUpdateTimeSeconds": 1291546800},{"contestId": 55,"contestName": "Codeforces Beta Round #51","handle": "nab","newRating": 1539,"oldRating": 1662,"rank": 417,"ratingUpdateTimeSeconds": 1294999200},{"contestId": 73,"contestName": "Codeforces Beta Round #66","handle": "nab","newRating": 1596,"oldRating": 1539,"rank": 250,"ratingUpdateTimeSeconds": 1302431400},{"contestId": 120,"contestName": "School Regional Team Contest, Saratov, 2011","handle": "nab","newRating": 1657,"oldRating": 1596,"rank": 161,"ratingUpdateTimeSeconds": 1318937400},{"contestId": 131,"contestName": "Codeforces Beta Round #95 (Div. 2)","handle": "nab","newRating": 1693,"oldRating": 1657,"rank": 130,"ratingUpdateTimeSeconds": 1322240400},{"contestId": 136,"contestName": "Codeforces Beta Round #97 (Div. 2)","handle": "nab","newRating": 1734,"oldRating": 1693,"rank": 56,"ratingUpdateTimeSeconds": 1323450300},{"contestId": 138,"contestName": "Codeforces Beta Round #99 (Div. 1)","handle": "nab","newRating": 1717,"oldRating": 1734,"rank": 249,"ratingUpdateTimeSeconds": 1324735200},{"contestId": 140,"contestName": "Codeforces Round #100","handle": "nab","newRating": 1933,"oldRating": 1717,"rank": 166,"ratingUpdateTimeSeconds": 1325696400},{"contestId": 145,"contestName": "Codeforces Round #104 (Div. 1)","handle": "nab","newRating": 2010,"oldRating": 1933,"rank": 73,"ratingUpdateTimeSeconds": 1327222800},{"contestId": 161,"contestName": "VK Cup 2012 Round 1","handle": "nab","newRating": 2141,"oldRating": 2010,"rank": 115,"ratingUpdateTimeSeconds": 1331485500},{"contestId": 163,"contestName": "VK Cup 2012 Round 2","handle": "nab","newRating": 2078,"oldRating": 2141,"rank": 237,"ratingUpdateTimeSeconds": 1332695100},{"contestId": 191,"contestName": "Codeforces Round #121 (Div. 1)","handle": "nab","newRating": 2026,"oldRating": 2078,"rank": 135,"ratingUpdateTimeSeconds": 1338139800},{"contestId": 193,"contestName": "Codeforces Round #122 (Div. 1)","handle": "nab","newRating": 2009,"oldRating": 2026,"rank": 115,"ratingUpdateTimeSeconds": 1338744600},{"contestId": 198,"contestName": "Codeforces Round #125 (Div. 1)","handle": "nab","newRating": 2045,"oldRating": 2009,"rank": 68,"ratingUpdateTimeSeconds": 1340386200},{"contestId": 321,"contestName": "Codeforces Round #190 (Div. 1)","handle": "nab","newRating": 2146,"oldRating": 2045,"rank": 44,"ratingUpdateTimeSeconds": 1372440600},{"contestId": 343,"contestName": "Codeforces Round #200 (Div. 1)","handle": "nab","newRating": 2079,"oldRating": 2146,"rank": 234,"ratingUpdateTimeSeconds": 1379180400},{"contestId": 434,"contestName": "Codeforces Round #248 (Div. 1)","handle": "nab","newRating": 2182,"oldRating": 2079,"rank": 23,"ratingUpdateTimeSeconds": 1400922000},{"contestId": 436,"contestName": "Zepto Code Rush 2014","handle": "nab","newRating": 2074,"oldRating": 2182,"rank": 595,"ratingUpdateTimeSeconds": 1402682400},{"contestId": 449,"contestName": "Codeforces Round #257 (Div. 1)","handle": "nab","newRating": 1969,"oldRating": 2074,"rank": 513,"ratingUpdateTimeSeconds": 1405782000}],"status": "OK"}