{"result": [{"contestId": 1093,"contestName": "Educational Codeforces Round 56 (Rated for Div. 2)","handle": "PhilTheFish","newRating": 1540,"oldRating": 1500,"rank": 1009,"ratingUpdateTimeSeconds": 1544891700},{"contestId": 1081,"contestName": "Avito Cool Challenge 2018","handle": "PhilTheFish","newRating": 1587,"oldRating": 1540,"rank": 993,"ratingUpdateTimeSeconds": 1544979900},{"contestId": 1133,"contestName": "Codeforces Round #544 (Div. 3)","handle": "PhilTheFish","newRating": 1693,"oldRating": 1587,"rank": 107,"ratingUpdateTimeSeconds": 1551978300},{"contestId": 1136,"contestName": "Codeforces Round #546 (Div. 2)","handle": "PhilTheFish","newRating": 1654,"oldRating": 1693,"rank": 1417,"ratingUpdateTimeSeconds": 1552329300},{"contestId": 1139,"contestName": "Codeforces Round #548 (Div. 2)","handle": "PhilTheFish","newRating": 1729,"oldRating": 1654,"rank": 412,"ratingUpdateTimeSeconds": 1553189700},{"contestId": 1175,"contestName": "Educational Codeforces Round 66 (Rated for Div. 2)","handle": "PhilTheFish","newRating": 1700,"oldRating": 1729,"rank": 1495,"ratingUpdateTimeSeconds": 1559752500},{"contestId": 1201,"contestName": "Codeforces Round #577 (Div. 2)","handle": "PhilTheFish","newRating": 1809,"oldRating": 1700,"rank": 199,"ratingUpdateTimeSeconds": 1564943700},{"contestId": 1202,"contestName": "Educational Codeforces Round 70 (Rated for Div. 2)","handle": "PhilTheFish","newRating": 1830,"oldRating": 1809,"rank": 504,"ratingUpdateTimeSeconds": 1565195700},{"contestId": 1200,"contestName": "Codeforces Round #578 (Div. 2)","handle": "PhilTheFish","newRating": 1822,"oldRating": 1830,"rank": 971,"ratingUpdateTimeSeconds": 1565534100},{"contestId": 1204,"contestName": "Codeforces Round #581 (Div. 2)","handle": "PhilTheFish","newRating": 1783,"oldRating": 1822,"rank": 1738,"ratingUpdateTimeSeconds": 1566318900},{"contestId": 1238,"contestName": "Educational Codeforces Round 74 (Rated for Div. 2)","handle": "PhilTheFish","newRating": 1744,"oldRating": 1783,"rank": 1612,"ratingUpdateTimeSeconds": 1570553700},{"contestId": 1244,"contestName": "Codeforces Round #592 (Div. 2)","handle": "PhilTheFish","newRating": 1770,"oldRating": 1744,"rank": 685,"ratingUpdateTimeSeconds": 1570964700},{"contestId": 1245,"contestName": "Codeforces Round #597 (Div. 2)","handle": "PhilTheFish","newRating": 1890,"oldRating": 1770,"rank": 155,"ratingUpdateTimeSeconds": 1572626100},{"contestId": 1255,"contestName": "Codeforces Round #601 (Div. 2)","handle": "PhilTheFish","newRating": 2056,"oldRating": 1890,"rank": 13,"ratingUpdateTimeSeconds": 1574181300}],"status": "OK"}