{"result": [{"contestId": 452,"contestName": "MemSQL Start[c]UP 2.0 - Round 1","handle": "rui-de","newRating": 1570,"oldRating": 1500,"rank": 802,"ratingUpdateTimeSeconds": 1406489400},{"contestId": 454,"contestName": "Codeforces Round #259 (Div. 2)","handle": "rui-de","newRating": 1474,"oldRating": 1570,"rank": 2161,"ratingUpdateTimeSeconds": 1406914200},{"contestId": 456,"contestName": "Codeforces Round #260 (Div. 2)","handle": "rui-de","newRating": 1551,"oldRating": 1474,"rank": 616,"ratingUpdateTimeSeconds": 1407519000},{"contestId": 458,"contestName": "MemSQL Start[c]UP 2.0 - Round 2 - Online Round","handle": "rui-de","newRating": 1568,"oldRating": 1551,"rank": 533,"ratingUpdateTimeSeconds": 1407700800},{"contestId": 459,"contestName": "Codeforces Round #261 (Div. 2)","handle": "rui-de","newRating": 1485,"oldRating": 1568,"rank": 1211,"ratingUpdateTimeSeconds": 1408123800},{"contestId": 462,"contestName": "Codeforces Round #263 (Div. 2)","handle": "rui-de","newRating": 1491,"oldRating": 1485,"rank": 848,"ratingUpdateTimeSeconds": 1409068800},{"contestId": 463,"contestName": "Codeforces Round #264 (Div. 2)","handle": "rui-de","newRating": 1411,"oldRating": 1491,"rank": 1233,"ratingUpdateTimeSeconds": 1409391000},{"contestId": 465,"contestName": "Codeforces Round #265 (Div. 2)","handle": "rui-de","newRating": 1354,"oldRating": 1411,"rank": 1341,"ratingUpdateTimeSeconds": 1410111000},{"contestId": 467,"contestName": "Codeforces Round #267 (Div. 2)","handle": "rui-de","newRating": 1468,"oldRating": 1354,"rank": 958,"ratingUpdateTimeSeconds": 1411061400},{"contestId": 474,"contestName": "Codeforces Round #271 (Div. 2)","handle": "rui-de","newRating": 1402,"oldRating": 1468,"rank": 1234,"ratingUpdateTimeSeconds": 1412618400},{"contestId": 476,"contestName": "Codeforces Round #272 (Div. 2)","handle": "rui-de","newRating": 1477,"oldRating": 1402,"rank": 797,"ratingUpdateTimeSeconds": 1413129600},{"contestId": 478,"contestName": "Codeforces Round #273 (Div. 2)","handle": "rui-de","newRating": 1615,"oldRating": 1477,"rank": 440,"ratingUpdateTimeSeconds": 1413481200},{"contestId": 479,"contestName": "Codeforces Round #274 (Div. 2)","handle": "rui-de","newRating": 1561,"oldRating": 1615,"rank": 538,"ratingUpdateTimeSeconds": 1413716400},{"contestId": 483,"contestName": "Codeforces Round #275 (Div. 2)","handle": "rui-de","newRating": 1519,"oldRating": 1561,"rank": 650,"ratingUpdateTimeSeconds": 1414177800},{"contestId": 486,"contestName": "Codeforces Round #277 (Div. 2)","handle": "rui-de","newRating": 1552,"oldRating": 1519,"rank": 602,"ratingUpdateTimeSeconds": 1415725200},{"contestId": 489,"contestName": "Codeforces Round #277.5 (Div. 2)","handle": "rui-de","newRating": 1643,"oldRating": 1552,"rank": 319,"ratingUpdateTimeSeconds": 1416247500},{"contestId": 490,"contestName": "Codeforces Round #279 (Div. 2)","handle": "rui-de","newRating": 1611,"oldRating": 1643,"rank": 356,"ratingUpdateTimeSeconds": 1416742800},{"contestId": 492,"contestName": "Codeforces Round #280 (Div. 2)","handle": "rui-de","newRating": 1699,"oldRating": 1611,"rank": 155,"ratingUpdateTimeSeconds": 1417458600},{"contestId": 495,"contestName": "Codeforces Round #282 (Div. 2)","handle": "rui-de","newRating": 1596,"oldRating": 1699,"rank": 1404,"ratingUpdateTimeSeconds": 1418495400},{"contestId": 500,"contestName": "Good Bye 2014","handle": "rui-de","newRating": 1584,"oldRating": 1596,"rank": 1866,"ratingUpdateTimeSeconds": 1419960600},{"contestId": 508,"contestName": "Codeforces Round #288 (Div. 2)","handle": "rui-de","newRating": 1623,"oldRating": 1584,"rank": 405,"ratingUpdateTimeSeconds": 1422383400},{"contestId": 509,"contestName": "Codeforces Round #289 (Div. 2, ACM ICPC Rules)","handle": "rui-de","newRating": 1673,"oldRating": 1623,"rank": 241,"ratingUpdateTimeSeconds": 1422716400},{"contestId": 510,"contestName": "Codeforces Round #290 (Div. 2)","handle": "rui-de","newRating": 1751,"oldRating": 1673,"rank": 70,"ratingUpdateTimeSeconds": 1422902100},{"contestId": 513,"contestName": "Rockethon 2015","handle": "rui-de","newRating": 1842,"oldRating": 1751,"rank": 753,"ratingUpdateTimeSeconds": 1423340100},{"contestId": 528,"contestName": "Codeforces Round #296 (Div. 1)","handle": "rui-de","newRating": 1853,"oldRating": 1842,"rank": 465,"ratingUpdateTimeSeconds": 1426617900},{"contestId": 524,"contestName": "VK Cup 2015 - Round 1","handle": "rui-de","newRating": 1802,"oldRating": 1853,"rank": 307,"ratingUpdateTimeSeconds": 1426953600},{"contestId": 532,"contestName": "VK Cup 2015 - Round 2","handle": "rui-de","newRating": 1758,"oldRating": 1802,"rank": 234,"ratingUpdateTimeSeconds": 1429295400},{"contestId": 542,"contestName": "VK Cup 2015 - Round 3 (unofficial online mirror, Div. 1 only)","handle": "rui-de","newRating": 1722,"oldRating": 1758,"rank": 242,"ratingUpdateTimeSeconds": 1430677800},{"contestId": 547,"contestName": "Codeforces Round #305 (Div. 1)","handle": "rui-de","newRating": 1661,"oldRating": 1722,"rank": 632,"ratingUpdateTimeSeconds": 1432665300},{"contestId": 588,"contestName": "Codeforces Round #326 (Div. 2)","handle": "rui-de","newRating": 1693,"oldRating": 1661,"rank": 292,"ratingUpdateTimeSeconds": 1444935600},{"contestId": 592,"contestName": "Codeforces Round #328 (Div. 2)","handle": "rui-de","newRating": 1673,"oldRating": 1693,"rank": 924,"ratingUpdateTimeSeconds": 1446316200},{"contestId": 596,"contestName": "Codeforces Round #331 (Div. 2)","handle": "rui-de","newRating": 1645,"oldRating": 1673,"rank": 853,"ratingUpdateTimeSeconds": 1447612500},{"contestId": 602,"contestName": "Codeforces Round #333 (Div. 2)","handle": "rui-de","newRating": 1770,"oldRating": 1645,"rank": 108,"ratingUpdateTimeSeconds": 1448390100},{"contestId": 611,"contestName": "Good Bye 2015","handle": "rui-de","newRating": 1840,"oldRating": 1770,"rank": 540,"ratingUpdateTimeSeconds": 1451498700},{"contestId": 625,"contestName": "Codeforces Round #342 (Div. 2)","handle": "rui-de","newRating": 1795,"oldRating": 1840,"rank": 638,"ratingUpdateTimeSeconds": 1454843100},{"contestId": 635,"contestName": "8VC Venture Cup 2016 - Final Round (Div. 2 Edition)","handle": "rui-de","newRating": 1883,"oldRating": 1795,"rank": 49,"ratingUpdateTimeSeconds": 1456690200},{"contestId": 631,"contestName": "Codeforces Round #344 (Div. 2)","handle": "rui-de","newRating": 2024,"oldRating": 1883,"rank": 14,"ratingUpdateTimeSeconds": 1457030100},{"contestId": 650,"contestName": "Codeforces Round #345 (Div. 1)","handle": "rui-de","newRating": 1989,"oldRating": 2024,"rank": 353,"ratingUpdateTimeSeconds": 1457349900},{"contestId": 645,"contestName": "CROC 2016 - Elimination Round","handle": "rui-de","newRating": 1928,"oldRating": 1989,"rank": 382,"ratingUpdateTimeSeconds": 1458326100},{"contestId": 653,"contestName": "IndiaHacks 2016 - Online Edition (Div. 1 + Div. 2)","handle": "rui-de","newRating": 1787,"oldRating": 1928,"rank": 1446,"ratingUpdateTimeSeconds": 1458383700},{"contestId": 639,"contestName": "VK Cup 2016 - Round 1","handle": "rui-de","newRating": 1852,"oldRating": 1787,"rank": 238,"ratingUpdateTimeSeconds": 1459190100},{"contestId": 659,"contestName": "Codeforces Round #346 (Div. 2)","handle": "rui-de","newRating": 1768,"oldRating": 1852,"rank": 1305,"ratingUpdateTimeSeconds": 1459362900},{"contestId": 641,"contestName": "VK Cup 2016 - Round 2","handle": "rui-de","newRating": 1729,"oldRating": 1768,"rank": 326,"ratingUpdateTimeSeconds": 1461522900},{"contestId": 670,"contestName": "Codeforces Round #350 (Div. 2)","handle": "rui-de","newRating": 1839,"oldRating": 1729,"rank": 72,"ratingUpdateTimeSeconds": 1462473300},{"contestId": 672,"contestName": "Codeforces Round #352 (Div. 2)","handle": "rui-de","newRating": 1895,"oldRating": 1839,"rank": 105,"ratingUpdateTimeSeconds": 1462991700},{"contestId": 675,"contestName": "Codeforces Round #353 (Div. 2)","handle": "rui-de","newRating": 1936,"oldRating": 1895,"rank": 119,"ratingUpdateTimeSeconds": 1463423700},{"contestId": 685,"contestName": "Codeforces Round #359 (Div. 1)","handle": "rui-de","newRating": 1961,"oldRating": 1936,"rank": 245,"ratingUpdateTimeSeconds": 1466706900},{"contestId": 687,"contestName": "Codeforces Round #360 (Div. 1)","handle": "rui-de","newRating": 1868,"oldRating": 1961,"rank": 538,"ratingUpdateTimeSeconds": 1467227100},{"contestId": 697,"contestName": "Codeforces Round #362 (Div. 2)","handle": "rui-de","newRating": 1784,"oldRating": 1868,"rank": 1221,"ratingUpdateTimeSeconds": 1468522200},{"contestId": 699,"contestName": "Codeforces Round #363 (Div. 2)","handle": "rui-de","newRating": 1860,"oldRating": 1784,"rank": 133,"ratingUpdateTimeSeconds": 1468941600},{"contestId": 701,"contestName": "Codeforces Round #364 (Div. 2)","handle": "rui-de","newRating": 2025,"oldRating": 1860,"rank": 13,"ratingUpdateTimeSeconds": 1469212500},{"contestId": 708,"contestName": "AIM Tech Round 3 (Div. 1)","handle": "rui-de","newRating": 1948,"oldRating": 2025,"rank": 530,"ratingUpdateTimeSeconds": 1472063700},{"contestId": 722,"contestName": "Intel Code Challenge Elimination Round (Div. 1 + Div. 2, combined)","handle": "rui-de","newRating": 1896,"oldRating": 1948,"rank": 1167,"ratingUpdateTimeSeconds": 1475337900},{"contestId": 724,"contestName": "Intel Code Challenge Final Round (Div. 1 + Div. 2, Combined)","handle": "rui-de","newRating": 1944,"oldRating": 1896,"rank": 362,"ratingUpdateTimeSeconds": 1475939700},{"contestId": 737,"contestName": "Codeforces Round #380 (Div. 1, Rated, Based on Technocup 2017 - Elimination Round 2)","handle": "rui-de","newRating": 1973,"oldRating": 1944,"rank": 210,"ratingUpdateTimeSeconds": 1479639900},{"contestId": 739,"contestName": "Codeforces Round #381 (Div. 1)","handle": "rui-de","newRating": 1995,"oldRating": 1973,"rank": 258,"ratingUpdateTimeSeconds": 1479926100},{"contestId": 757,"contestName": "Codecraft-17 and Codeforces Round #391 (Div. 1 + Div. 2, combined)","handle": "rui-de","newRating": 1907,"oldRating": 1995,"rank": 1498,"ratingUpdateTimeSeconds": 1484246100},{"contestId": 755,"contestName": "8VC Venture Cup 2017 - Elimination Round","handle": "rui-de","newRating": 1909,"oldRating": 1907,"rank": 656,"ratingUpdateTimeSeconds": 1484507100},{"contestId": 768,"contestName": "Divide by Zero 2017 and Codeforces Round #399 (Div. 1 + Div. 2, combined)","handle": "rui-de","newRating": 1971,"oldRating": 1909,"rank": 330,"ratingUpdateTimeSeconds": 1487616300},{"contestId": 771,"contestName": "VK Cup 2017 - Round 1","handle": "rui-de","newRating": 1992,"oldRating": 1971,"rank": 81,"ratingUpdateTimeSeconds": 1489858500},{"contestId": 788,"contestName": "Codeforces Round #407 (Div. 1)","handle": "rui-de","newRating": 1926,"oldRating": 1992,"rank": 406,"ratingUpdateTimeSeconds": 1490810700},{"contestId": 772,"contestName": "VK Cup 2017 - Round 2","handle": "rui-de","newRating": 1880,"oldRating": 1926,"rank": 130,"ratingUpdateTimeSeconds": 1492364100},{"contestId": 798,"contestName": "Codeforces Round #410 (Div. 2)","handle": "rui-de","newRating": 1925,"oldRating": 1880,"rank": 132,"ratingUpdateTimeSeconds": 1492792500},{"contestId": 804,"contestName": "Codeforces Round #411 (Div. 1)","handle": "rui-de","newRating": 1907,"oldRating": 1925,"rank": 410,"ratingUpdateTimeSeconds": 1493916600},{"contestId": 815,"contestName": "Codeforces Round #419 (Div. 1)","handle": "rui-de","newRating": 1871,"oldRating": 1907,"rank": 487,"ratingUpdateTimeSeconds": 1497717300},{"contestId": 834,"contestName": "Codeforces Round #426 (Div. 2)","handle": "rui-de","newRating": 1845,"oldRating": 1871,"rank": 600,"ratingUpdateTimeSeconds": 1501432500},{"contestId": 835,"contestName": "Codeforces Round #427 (Div. 2)","handle": "rui-de","newRating": 1866,"oldRating": 1845,"rank": 260,"ratingUpdateTimeSeconds": 1501518900},{"contestId": 841,"contestName": "Codeforces Round #429 (Div. 2)","handle": "rui-de","newRating": 1930,"oldRating": 1866,"rank": 102,"ratingUpdateTimeSeconds": 1503075900},{"contestId": 843,"contestName": "AIM Tech Round 4 (Div. 1)","handle": "rui-de","newRating": 1890,"oldRating": 1930,"rank": 406,"ratingUpdateTimeSeconds": 1503601500},{"contestId": 842,"contestName": "Codeforces Round #430 (Div. 2)","handle": "rui-de","newRating": 1799,"oldRating": 1890,"rank": 1690,"ratingUpdateTimeSeconds": 1504026300},{"contestId": 851,"contestName": "Codeforces Round #432 (Div. 2, based on IndiaHacks Final Round 2017)","handle": "rui-de","newRating": 1779,"oldRating": 1799,"rank": 682,"ratingUpdateTimeSeconds": 1504544700},{"contestId": 859,"contestName": "MemSQL Start[c]UP 3.0 - Round 1","handle": "rui-de","newRating": 1745,"oldRating": 1779,"rank": 933,"ratingUpdateTimeSeconds": 1505592300},{"contestId": 855,"contestName": "Manthan, Codefest 17","handle": "rui-de","newRating": 1862,"oldRating": 1745,"rank": 214,"ratingUpdateTimeSeconds": 1506272700},{"contestId": 864,"contestName": "Codeforces Round #436 (Div. 2)","handle": "rui-de","newRating": 1868,"oldRating": 1862,"rank": 243,"ratingUpdateTimeSeconds": 1506342900},{"contestId": 876,"contestName": "Codeforces Round #441 (Div. 2, by Moscow Team Olympiad)","handle": "rui-de","newRating": 1938,"oldRating": 1868,"rank": 79,"ratingUpdateTimeSeconds": 1508159100},{"contestId": 878,"contestName": "Codeforces Round #443 (Div. 1)","handle": "rui-de","newRating": 1860,"oldRating": 1938,"rank": 415,"ratingUpdateTimeSeconds": 1509036300},{"contestId": 894,"contestName": "Codeforces Round #447 (Div. 2)","handle": "rui-de","newRating": 1889,"oldRating": 1860,"rank": 185,"ratingUpdateTimeSeconds": 1511106900},{"contestId": 895,"contestName": "Codeforces Round #448 (Div. 2)","handle": "rui-de","newRating": 2045,"oldRating": 1889,"rank": 12,"ratingUpdateTimeSeconds": 1511719500},{"contestId": 913,"contestName": "Hello 2018","handle": "rui-de","newRating": 2086,"oldRating": 2045,"rank": 334,"ratingUpdateTimeSeconds": 1515431700},{"contestId": 914,"contestName": "Codecraft-18 and Codeforces Round #458 (Div. 1 + Div. 2, combined)","handle": "rui-de","newRating": 2032,"oldRating": 2086,"rank": 768,"ratingUpdateTimeSeconds": 1516473300},{"contestId": 917,"contestName": "Codeforces Round #459 (Div. 1)","handle": "rui-de","newRating": 2039,"oldRating": 2032,"rank": 193,"ratingUpdateTimeSeconds": 1517243700},{"contestId": 933,"contestName": "Codeforces Round #462 (Div. 1)","handle": "rui-de","newRating": 1988,"oldRating": 2039,"rank": 403,"ratingUpdateTimeSeconds": 1518617100},{"contestId": 932,"contestName": "ICM Technex 2018 and Codeforces Round #463 (Div. 1 + Div. 2, combined)","handle": "rui-de","newRating": 2009,"oldRating": 1988,"rank": 393,"ratingUpdateTimeSeconds": 1518712500},{"contestId": 936,"contestName": "Codeforces Round #467 (Div. 1)","handle": "rui-de","newRating": 2067,"oldRating": 2009,"rank": 144,"ratingUpdateTimeSeconds": 1519581900},{"contestId": 930,"contestName": "Codeforces Round #468 (Div. 1, based on Technocup 2018 Final Round)","handle": "rui-de","newRating": 2032,"oldRating": 2067,"rank": 318,"ratingUpdateTimeSeconds": 1520184900},{"contestId": 923,"contestName": "VK Cup 2018 - Round 1","handle": "rui-de","newRating": 2011,"oldRating": 2032,"rank": 165,"ratingUpdateTimeSeconds": 1520703300},{"contestId": 924,"contestName": "VK Cup 2018 - Round 2","handle": "rui-de","newRating": 1980,"oldRating": 2011,"rank": 148,"ratingUpdateTimeSeconds": 1521913800},{"contestId": 963,"contestName": "Tinkoff Internship Warmup Round 2018 and Codeforces Round #475 (Div. 1)","handle": "rui-de","newRating": 1965,"oldRating": 1980,"rank": 309,"ratingUpdateTimeSeconds": 1523981100},{"contestId": 966,"contestName": "Codeforces Round #477 (rated, Div. 1, based on VK Cup 2018 Round 3)","handle": "rui-de","newRating": 2158,"oldRating": 1965,"rank": 39,"ratingUpdateTimeSeconds": 1525016700},{"contestId": 981,"contestName": "Avito Code Challenge 2018","handle": "rui-de","newRating": 2211,"oldRating": 2158,"rank": 138,"ratingUpdateTimeSeconds": 1527443400},{"contestId": 1023,"contestName": "Codeforces Round #504 (rated, Div. 1 + Div. 2, based on VK Cup 2018 Final)","handle": "rui-de","newRating": 2222,"oldRating": 2211,"rank": 234,"ratingUpdateTimeSeconds": 1534524600},{"contestId": 1025,"contestName": "Codeforces Round #505 (rated, Div. 1 + Div. 2, based on VK Cup 2018 Final)","handle": "rui-de","newRating": 2278,"oldRating": 2222,"rank": 123,"ratingUpdateTimeSeconds": 1534693800},{"contestId": 1028,"contestName": "AIM Tech Round 5 (rated, Div. 1 + Div. 2)","handle": "rui-de","newRating": 2315,"oldRating": 2278,"rank": 123,"ratingUpdateTimeSeconds": 1535395800},{"contestId": 1037,"contestName": "Manthan, Codefest 18 (rated, Div. 1 + Div. 2)","handle": "rui-de","newRating": 2339,"oldRating": 2315,"rank": 126,"ratingUpdateTimeSeconds": 1535906100},{"contestId": 1039,"contestName": "Codeforces Round #507 (Div. 1, based on Olympiad of Metropolises)","handle": "rui-de","newRating": 2321,"oldRating": 2339,"rank": 106,"ratingUpdateTimeSeconds": 1536172500},{"contestId": 1034,"contestName": "Codeforces Round #511 (Div. 1)","handle": "rui-de","newRating": 2223,"oldRating": 2321,"rank": 400,"ratingUpdateTimeSeconds": 1537547700},{"contestId": 1060,"contestName": "Codeforces Round #513 by Barcelona Bootcamp (rated, Div. 1 + Div. 2)","handle": "rui-de","newRating": 2218,"oldRating": 2223,"rank": 238,"ratingUpdateTimeSeconds": 1538645700},{"contestId": 1063,"contestName": "Codeforces Round #516 (Div. 1, by Moscow Team Olympiad)","handle": "rui-de","newRating": 2146,"oldRating": 2218,"rank": 338,"ratingUpdateTimeSeconds": 1539518700},{"contestId": 1054,"contestName": "Mail.Ru Cup 2018 Round 1","handle": "rui-de","newRating": 2273,"oldRating": 2146,"rank": 52,"ratingUpdateTimeSeconds": 1539889500},{"contestId": 1071,"contestName": "Codeforces Round #517 (Div. 1, based on Technocup 2019 Elimination Round 2)","handle": "rui-de","newRating": 2273,"oldRating": 2273,"rank": 133,"ratingUpdateTimeSeconds": 1540116600},{"contestId": 1067,"contestName": "Codeforces Round #518 (Div. 1) [Thanks, Mail.Ru!]","handle": "rui-de","newRating": 2235,"oldRating": 2273,"rank": 185,"ratingUpdateTimeSeconds": 1540406100},{"contestId": 1074,"contestName": "Lyft Level 5 Challenge 2018 - Final Round (Open Div. 1)","handle": "rui-de","newRating": 2313,"oldRating": 2235,"rank": 43,"ratingUpdateTimeSeconds": 1541364000},{"contestId": 1055,"contestName": "Mail.Ru Cup 2018 Round 2","handle": "rui-de","newRating": 2231,"oldRating": 2313,"rank": 478,"ratingUpdateTimeSeconds": 1541869500},{"contestId": 1056,"contestName": "Mail.Ru Cup 2018 Round 3","handle": "rui-de","newRating": 2304,"oldRating": 2231,"rank": 85,"ratingUpdateTimeSeconds": 1543172700},{"contestId": 1083,"contestName": "Codeforces Round #526 (Div. 1)","handle": "rui-de","newRating": 2240,"oldRating": 2304,"rank": 210,"ratingUpdateTimeSeconds": 1544466900},{"contestId": 1081,"contestName": "Avito Cool Challenge 2018","handle": "rui-de","newRating": 2192,"oldRating": 2240,"rank": 407,"ratingUpdateTimeSeconds": 1544979900},{"contestId": 1103,"contestName": "Codeforces Round #534 (Div. 1)","handle": "rui-de","newRating": 2139,"oldRating": 2192,"rank": 333,"ratingUpdateTimeSeconds": 1548174900},{"contestId": 1110,"contestName": "Codeforces Global Round 1","handle": "rui-de","newRating": 2228,"oldRating": 2139,"rank": 168,"ratingUpdateTimeSeconds": 1549553700},{"contestId": 1109,"contestName": "Codeforces Round #539 (Div. 1)","handle": "rui-de","newRating": 2236,"oldRating": 2228,"rank": 153,"ratingUpdateTimeSeconds": 1550343900},{"contestId": 1119,"contestName": "Codeforces Global Round 2","handle": "rui-de","newRating": 2278,"oldRating": 2236,"rank": 188,"ratingUpdateTimeSeconds": 1554557700},{"contestId": 1149,"contestName": "Codeforces Round #556 (Div. 1)","handle": "rui-de","newRating": 2270,"oldRating": 2278,"rank": 234,"ratingUpdateTimeSeconds": 1556555700},{"contestId": 1161,"contestName": "Codeforces Round #557 (Div. 1) [based on Forethought Future Cup - Final Round]","handle": "rui-de","newRating": 2306,"oldRating": 2270,"rank": 94,"ratingUpdateTimeSeconds": 1556996700},{"contestId": 1158,"contestName": "Codeforces Round #559 (Div. 1)","handle": "rui-de","newRating": 2296,"oldRating": 2306,"rank": 144,"ratingUpdateTimeSeconds": 1557678900},{"contestId": 1198,"contestName": "Codeforces Round #576 (Div. 1)","handle": "rui-de","newRating": 2340,"oldRating": 2296,"rank": 108,"ratingUpdateTimeSeconds": 1564504500},{"contestId": 1214,"contestName": "Codeforces Round #583 (Div. 1 + Div. 2, based on Olympiad of Metropolises)","handle": "rui-de","newRating": 2369,"oldRating": 2340,"rank": 116,"ratingUpdateTimeSeconds": 1567596900},{"contestId": 1209,"contestName": "Codeforces Round #584 - Dasha Code Championship - Elimination Round (rated, open for everyone, Div. 1 + Div. 2)","handle": "rui-de","newRating": 2296,"oldRating": 2369,"rank": 646,"ratingUpdateTimeSeconds": 1568475300},{"contestId": 1220,"contestName": "Codeforces Round #586 (Div. 1 + Div. 2)","handle": "rui-de","newRating": 2332,"oldRating": 2296,"rank": 134,"ratingUpdateTimeSeconds": 1568829900},{"contestId": 1237,"contestName": "Codeforces Global Round 5","handle": "rui-de","newRating": 2289,"oldRating": 2332,"rank": 535,"ratingUpdateTimeSeconds": 1571245500},{"contestId": 1239,"contestName": "Codeforces Round #594 (Div. 1)","handle": "rui-de","newRating": 2248,"oldRating": 2289,"rank": 273,"ratingUpdateTimeSeconds": 1571569500},{"contestId": 1254,"contestName": "Codeforces Round #601 (Div. 1)","handle": "rui-de","newRating": 2211,"oldRating": 2248,"rank": 341,"ratingUpdateTimeSeconds": 1574181300},{"contestId": 1261,"contestName": "Codeforces Round #602 (Div. 1, based on Technocup 2020 Elimination Round 3)","handle": "rui-de","newRating": 2228,"oldRating": 2211,"rank": 170,"ratingUpdateTimeSeconds": 1574589900}],"status": "OK"}