{"result": [{"contestId": 23,"contestName": "Codeforces Beta Round #23","handle": "v.haralampiev","newRating": 1680,"oldRating": 1500,"rank": 61,"ratingUpdateTimeSeconds": 1278694800},{"contestId": 28,"contestName": "Codeforces Beta Round #28 (Codeforces format)","handle": "v.haralampiev","newRating": 1736,"oldRating": 1680,"rank": 78,"ratingUpdateTimeSeconds": 1284742800},{"contestId": 37,"contestName": "Codeforces Beta Round #37","handle": "v.haralampiev","newRating": 1701,"oldRating": 1736,"rank": 162,"ratingUpdateTimeSeconds": 1288026000},{"contestId": 51,"contestName": "Codeforces Beta Round #48","handle": "v.haralampiev","newRating": 1917,"oldRating": 1701,"rank": 20,"ratingUpdateTimeSeconds": 1293561000},{"contestId": 54,"contestName": "Codeforces Beta Round #50","handle": "v.haralampiev","newRating": 1851,"oldRating": 1917,"rank": 105,"ratingUpdateTimeSeconds": 1294740900},{"contestId": 57,"contestName": "Codeforces Beta Round #53","handle": "v.haralampiev","newRating": 1778,"oldRating": 1851,"rank": 173,"ratingUpdateTimeSeconds": 1295978400},{"contestId": 60,"contestName": "Codeforces Beta Round #56","handle": "v.haralampiev","newRating": 1780,"oldRating": 1778,"rank": 166,"ratingUpdateTimeSeconds": 1298138400},{"contestId": 70,"contestName": "Codeforces Beta Round #64","handle": "v.haralampiev","newRating": 1953,"oldRating": 1780,"rank": 48,"ratingUpdateTimeSeconds": 1301162400},{"contestId": 74,"contestName": "Codeforces Beta Round #68","handle": "v.haralampiev","newRating": 1943,"oldRating": 1953,"rank": 135,"ratingUpdateTimeSeconds": 1302886800},{"contestId": 87,"contestName": "Codeforces Beta Round #73 (Div. 1 Only)","handle": "v.haralampiev","newRating": 2037,"oldRating": 1943,"rank": 58,"ratingUpdateTimeSeconds": 1307466000},{"contestId": 109,"contestName": "Codeforces Beta Round #84 (Div. 1 Only)","handle": "v.haralampiev","newRating": 2124,"oldRating": 2037,"rank": 51,"ratingUpdateTimeSeconds": 1314640800},{"contestId": 115,"contestName": "Codeforces Beta Round #87 (Div. 1 Only)","handle": "v.haralampiev","newRating": 2083,"oldRating": 2124,"rank": 147,"ratingUpdateTimeSeconds": 1316106000},{"contestId": 126,"contestName": "Codeforces Beta Round #93 (Div. 1 Only)","handle": "v.haralampiev","newRating": 2038,"oldRating": 2083,"rank": 163,"ratingUpdateTimeSeconds": 1320865200},{"contestId": 138,"contestName": "Codeforces Beta Round #99 (Div. 1)","handle": "v.haralampiev","newRating": 2094,"oldRating": 2038,"rank": 66,"ratingUpdateTimeSeconds": 1324735200},{"contestId": 161,"contestName": "VK Cup 2012 Round 1","handle": "v.haralampiev","newRating": 2169,"oldRating": 2094,"rank": 138,"ratingUpdateTimeSeconds": 1331485500},{"contestId": 163,"contestName": "VK Cup 2012 Round 2","handle": "v.haralampiev","newRating": 2205,"oldRating": 2169,"rank": 109,"ratingUpdateTimeSeconds": 1332695100},{"contestId": 173,"contestName": "Croc Champ 2012 - Round 1","handle": "v.haralampiev","newRating": 2282,"oldRating": 2205,"rank": 22,"ratingUpdateTimeSeconds": 1333731600},{"contestId": 164,"contestName": "VK Cup 2012 Round 3","handle": "v.haralampiev","newRating": 2248,"oldRating": 2282,"rank": 97,"ratingUpdateTimeSeconds": 1333904700},{"contestId": 176,"contestName": "Croc Champ 2012 - Round 2","handle": "v.haralampiev","newRating": 2137,"oldRating": 2248,"rank": 235,"ratingUpdateTimeSeconds": 1334941500},{"contestId": 213,"contestName": "Codeforces Round #131 (Div. 1)","handle": "v.haralampiev","newRating": 2075,"oldRating": 2137,"rank": 138,"ratingUpdateTimeSeconds": 1343669400},{"contestId": 217,"contestName": "Codeforces Round #134 (Div. 1)","handle": "v.haralampiev","newRating": 2013,"oldRating": 2075,"rank": 176,"ratingUpdateTimeSeconds": 1345280700},{"contestId": 220,"contestName": "Codeforces Round #136 (Div. 1)","handle": "v.haralampiev","newRating": 2096,"oldRating": 2013,"rank": 57,"ratingUpdateTimeSeconds": 1346434200},{"contestId": 226,"contestName": "Codeforces Round #140 (Div. 1)","handle": "v.haralampiev","newRating": 2189,"oldRating": 2096,"rank": 15,"ratingUpdateTimeSeconds": 1348507800},{"contestId": 229,"contestName": "Codeforces Round #142 (Div. 1)","handle": "v.haralampiev","newRating": 2227,"oldRating": 2189,"rank": 41,"ratingUpdateTimeSeconds": 1349112900},{"contestId": 241,"contestName": "Bayan 2012-2013 Elimination Round (ACM ICPC Rules, English statements)","handle": "v.haralampiev","newRating": 2185,"oldRating": 2227,"rank": 104,"ratingUpdateTimeSeconds": 1351794600},{"contestId": 238,"contestName": "Codeforces Round #148 (Div. 1)","handle": "v.haralampiev","newRating": 2227,"oldRating": 2185,"rank": 30,"ratingUpdateTimeSeconds": 1352052000},{"contestId": 249,"contestName": "Codeforces Round #152 (Div. 1)","handle": "v.haralampiev","newRating": 2182,"oldRating": 2227,"rank": 73,"ratingUpdateTimeSeconds": 1353865500},{"contestId": 273,"contestName": "Codeforces Round #167 (Div. 1)","handle": "v.haralampiev","newRating": 2110,"oldRating": 2182,"rank": 201,"ratingUpdateTimeSeconds": 1360776600},{"contestId": 277,"contestName": "Codeforces Round #170 (Div. 1)","handle": "v.haralampiev","newRating": 2228,"oldRating": 2110,"rank": 20,"ratingUpdateTimeSeconds": 1362072600},{"contestId": 292,"contestName": "Croc Champ 2013 - Round 1","handle": "v.haralampiev","newRating": 2264,"oldRating": 2228,"rank": 97,"ratingUpdateTimeSeconds": 1366047300},{"contestId": 293,"contestName": "Croc Champ 2013 - Round 2","handle": "v.haralampiev","newRating": 2186,"oldRating": 2264,"rank": 254,"ratingUpdateTimeSeconds": 1366652700},{"contestId": 325,"contestName": "MemSQL start[c]up Round 1","handle": "v.haralampiev","newRating": 2184,"oldRating": 2186,"rank": 122,"ratingUpdateTimeSeconds": 1373742000},{"contestId": 333,"contestName": "Codeforces Round #194 (Div. 1)","handle": "v.haralampiev","newRating": 2088,"oldRating": 2184,"rank": 313,"ratingUpdateTimeSeconds": 1374921000},{"contestId": 341,"contestName": "Codeforces Round #198 (Div. 1)","handle": "v.haralampiev","newRating": 2212,"oldRating": 2088,"rank": 15,"ratingUpdateTimeSeconds": 1377883800},{"contestId": 343,"contestName": "Codeforces Round #200 (Div. 1)","handle": "v.haralampiev","newRating": 2307,"oldRating": 2212,"rank": 18,"ratingUpdateTimeSeconds": 1379180400},{"contestId": 379,"contestName": "Good Bye 2013","handle": "v.haralampiev","newRating": 2343,"oldRating": 2307,"rank": 54,"ratingUpdateTimeSeconds": 1388424600},{"contestId": 418,"contestName": "RCC 2014 Warmup (Div. 1)","handle": "v.haralampiev","newRating": 2258,"oldRating": 2343,"rank": 175,"ratingUpdateTimeSeconds": 1397756400},{"contestId": 500,"contestName": "Good Bye 2014","handle": "v.haralampiev","newRating": 2324,"oldRating": 2258,"rank": 119,"ratingUpdateTimeSeconds": 1419960600},{"contestId": 524,"contestName": "VK Cup 2015 - Round 1","handle": "v.haralampiev","newRating": 2347,"oldRating": 2324,"rank": 80,"ratingUpdateTimeSeconds": 1426953600},{"contestId": 526,"contestName": "ZeptoLab Code Rush 2015","handle": "v.haralampiev","newRating": 2352,"oldRating": 2347,"rank": 164,"ratingUpdateTimeSeconds": 1428174300},{"contestId": 532,"contestName": "VK Cup 2015 - Round 2","handle": "v.haralampiev","newRating": 2346,"oldRating": 2352,"rank": 90,"ratingUpdateTimeSeconds": 1429295400}],"status": "OK"}