{"result": [{"contestId": 349,"contestName": "Codeforces Round #202 (Div. 2)","handle": "adedalic","newRating": 1662,"oldRating": 1500,"rank": 349,"ratingUpdateTimeSeconds": 1380303000},{"contestId": 350,"contestName": "Codeforces Round #203 (Div. 2)","handle": "adedalic","newRating": 1655,"oldRating": 1662,"rank": 291,"ratingUpdateTimeSeconds": 1380648600},{"contestId": 358,"contestName": "Codeforces Round #208 (Div. 2)","handle": "adedalic","newRating": 1595,"oldRating": 1655,"rank": 470,"ratingUpdateTimeSeconds": 1382722200},{"contestId": 402,"contestName": "Codeforces Round #236 (Div. 2)","handle": "adedalic","newRating": 1672,"oldRating": 1595,"rank": 164,"ratingUpdateTimeSeconds": 1394991000},{"contestId": 471,"contestName": "Codeforces Round #269 (Div. 2)","handle": "adedalic","newRating": 1717,"oldRating": 1672,"rank": 182,"ratingUpdateTimeSeconds": 1411752600},{"contestId": 480,"contestName": "Codeforces Round #274 (Div. 1)","handle": "adedalic","newRating": 1798,"oldRating": 1717,"rank": 336,"ratingUpdateTimeSeconds": 1413716400},{"contestId": 482,"contestName": "Codeforces Round #275 (Div. 1)","handle": "adedalic","newRating": 1858,"oldRating": 1798,"rank": 329,"ratingUpdateTimeSeconds": 1414177800},{"contestId": 494,"contestName": "Codeforces Round #282 (Div. 1)","handle": "adedalic","newRating": 1943,"oldRating": 1858,"rank": 303,"ratingUpdateTimeSeconds": 1418495400},{"contestId": 512,"contestName": "Codeforces Round #290 (Div. 1)","handle": "adedalic","newRating": 1881,"oldRating": 1943,"rank": 562,"ratingUpdateTimeSeconds": 1422902100},{"contestId": 528,"contestName": "Codeforces Round #296 (Div. 1)","handle": "adedalic","newRating": 2040,"oldRating": 1881,"rank": 158,"ratingUpdateTimeSeconds": 1426617900},{"contestId": 524,"contestName": "VK Cup 2015 - Round 1","handle": "adedalic","newRating": 2059,"oldRating": 2040,"rank": 180,"ratingUpdateTimeSeconds": 1426953600},{"contestId": 532,"contestName": "VK Cup 2015 - Round 2","handle": "adedalic","newRating": 1984,"oldRating": 2059,"rank": 319,"ratingUpdateTimeSeconds": 1429295400},{"contestId": 618,"contestName": "Wunder Fund Round 2016 (Div. 1 + Div. 2 combined)","handle": "adedalic","newRating": 1897,"oldRating": 1984,"rank": 1393,"ratingUpdateTimeSeconds": 1454094600},{"contestId": 624,"contestName": "AIM Tech Round (Div. 2)","handle": "adedalic","newRating": 1885,"oldRating": 1897,"rank": 357,"ratingUpdateTimeSeconds": 1454612700},{"contestId": 631,"contestName": "Codeforces Round #344 (Div. 2)","handle": "adedalic","newRating": 1935,"oldRating": 1885,"rank": 90,"ratingUpdateTimeSeconds": 1457030100},{"contestId": 639,"contestName": "VK Cup 2016 - Round 1","handle": "adedalic","newRating": 2017,"oldRating": 1935,"rank": 21,"ratingUpdateTimeSeconds": 1459190100},{"contestId": 641,"contestName": "VK Cup 2016 - Round 2","handle": "adedalic","newRating": 2012,"oldRating": 2017,"rank": 54,"ratingUpdateTimeSeconds": 1461522900},{"contestId": 643,"contestName": "VK Cup 2016 - Round 3","handle": "adedalic","newRating": 2081,"oldRating": 2012,"rank": 17,"ratingUpdateTimeSeconds": 1462644300},{"contestId": 679,"contestName": "Codeforces Round #356 (Div. 1)","handle": "adedalic","newRating": 2030,"oldRating": 2081,"rank": 393,"ratingUpdateTimeSeconds": 1465410900},{"contestId": 685,"contestName": "Codeforces Round #359 (Div. 1)","handle": "adedalic","newRating": 2046,"oldRating": 2030,"rank": 210,"ratingUpdateTimeSeconds": 1466706900},{"contestId": 695,"contestName": "VK Cup 2016 - Finals","handle": "adedalic","newRating": 2006,"oldRating": 2046,"rank": 18,"ratingUpdateTimeSeconds": 1467546600},{"contestId": 696,"contestName": "Codeforces Round #362 (Div. 1)","handle": "adedalic","newRating": 2059,"oldRating": 2006,"rank": 169,"ratingUpdateTimeSeconds": 1468522200},{"contestId": 708,"contestName": "AIM Tech Round 3 (Div. 1)","handle": "adedalic","newRating": 2039,"oldRating": 2059,"rank": 342,"ratingUpdateTimeSeconds": 1472063700},{"contestId": 724,"contestName": "Intel Code Challenge Final Round (Div. 1 + Div. 2, Combined)","handle": "adedalic","newRating": 2018,"oldRating": 2039,"rank": 534,"ratingUpdateTimeSeconds": 1475939700},{"contestId": 750,"contestName": "Good Bye 2016","handle": "adedalic","newRating": 2081,"oldRating": 2018,"rank": 328,"ratingUpdateTimeSeconds": 1483116300},{"contestId": 759,"contestName": "Codeforces Round #393 (Div. 1) (8VC Venture Cup 2017 - Final Round Div. 1 Edition)","handle": "adedalic","newRating": 2052,"oldRating": 2081,"rank": 209,"ratingUpdateTimeSeconds": 1485116100},{"contestId": 776,"contestName": "ICM Technex 2017 and Codeforces Round #400 (Div. 1 + Div. 2, combined)","handle": "adedalic","newRating": 2106,"oldRating": 2052,"rank": 229,"ratingUpdateTimeSeconds": 1487868900},{"contestId": 771,"contestName": "VK Cup 2017 - Round 1","handle": "adedalic","newRating": 2129,"oldRating": 2106,"rank": 75,"ratingUpdateTimeSeconds": 1489858500},{"contestId": 772,"contestName": "VK Cup 2017 - Round 2","handle": "adedalic","newRating": 2024,"oldRating": 2129,"rank": 243,"ratingUpdateTimeSeconds": 1492364100},{"contestId": 804,"contestName": "Codeforces Round #411 (Div. 1)","handle": "adedalic","newRating": 2119,"oldRating": 2024,"rank": 122,"ratingUpdateTimeSeconds": 1493916600},{"contestId": 833,"contestName": "Codeforces Round #426 (Div. 1)","handle": "adedalic","newRating": 2215,"oldRating": 2119,"rank": 75,"ratingUpdateTimeSeconds": 1501432500},{"contestId": 878,"contestName": "Codeforces Round #443 (Div. 1)","handle": "adedalic","newRating": 2164,"oldRating": 2215,"rank": 229,"ratingUpdateTimeSeconds": 1509036300},{"contestId": 901,"contestName": "Codeforces Round #453 (Div. 1)","handle": "adedalic","newRating": 2091,"oldRating": 2164,"rank": 330,"ratingUpdateTimeSeconds": 1513704900},{"contestId": 906,"contestName": "Codeforces Round #454 (Div. 1, based on Technocup 2018 Elimination Round 4)","handle": "adedalic","newRating": 2199,"oldRating": 2091,"rank": 73,"ratingUpdateTimeSeconds": 1514045100},{"contestId": 908,"contestName": "Good Bye 2017","handle": "adedalic","newRating": 2131,"oldRating": 2199,"rank": 921,"ratingUpdateTimeSeconds": 1514571000},{"contestId": 913,"contestName": "Hello 2018","handle": "adedalic","newRating": 2147,"oldRating": 2131,"rank": 342,"ratingUpdateTimeSeconds": 1515431700},{"contestId": 914,"contestName": "Codecraft-18 and Codeforces Round #458 (Div. 1 + Div. 2, combined)","handle": "adedalic","newRating": 2112,"oldRating": 2147,"rank": 495,"ratingUpdateTimeSeconds": 1516473300},{"contestId": 933,"contestName": "Codeforces Round #462 (Div. 1)","handle": "adedalic","newRating": 2261,"oldRating": 2112,"rank": 37,"ratingUpdateTimeSeconds": 1518617100},{"contestId": 932,"contestName": "ICM Technex 2018 and Codeforces Round #463 (Div. 1 + Div. 2, combined)","handle": "adedalic","newRating": 2232,"oldRating": 2261,"rank": 303,"ratingUpdateTimeSeconds": 1518712500},{"contestId": 949,"contestName": "Codeforces Round #469 (Div. 1)","handle": "adedalic","newRating": 2240,"oldRating": 2232,"rank": 131,"ratingUpdateTimeSeconds": 1520592000},{"contestId": 923,"contestName": "VK Cup 2018 - Round 1","handle": "adedalic","newRating": 2320,"oldRating": 2240,"rank": 27,"ratingUpdateTimeSeconds": 1520703300},{"contestId": 924,"contestName": "VK Cup 2018 - Round 2","handle": "adedalic","newRating": 2409,"oldRating": 2320,"rank": 26,"ratingUpdateTimeSeconds": 1521913800},{"contestId": 960,"contestName": "Divide by Zero 2018 and Codeforces Round #474 (Div. 1 + Div. 2, combined)","handle": "adedalic","newRating": 2362,"oldRating": 2409,"rank": 207,"ratingUpdateTimeSeconds": 1523126100},{"contestId": 925,"contestName": "VK Cup 2018 - Round 3","handle": "adedalic","newRating": 2386,"oldRating": 2362,"rank": 24,"ratingUpdateTimeSeconds": 1525016700},{"contestId": 983,"contestName": "Codeforces Round #483 (Div. 1) [Thanks, Botan Investments and Victor Shaburov!]","handle": "adedalic","newRating": 2262,"oldRating": 2386,"rank": 439,"ratingUpdateTimeSeconds": 1526402700},{"contestId": 981,"contestName": "Avito Code Challenge 2018","handle": "adedalic","newRating": 2304,"oldRating": 2262,"rank": 111,"ratingUpdateTimeSeconds": 1527443400},{"contestId": 986,"contestName": "Codeforces Round #485 (Div. 1)","handle": "adedalic","newRating": 2375,"oldRating": 2304,"rank": 60,"ratingUpdateTimeSeconds": 1527615900},{"contestId": 995,"contestName": "Codeforces Round #492 (Div. 1) [Thanks, uDebug!]","handle": "adedalic","newRating": 2269,"oldRating": 2375,"rank": 324,"ratingUpdateTimeSeconds": 1529865300},{"contestId": 997,"contestName": "Codeforces Round #493 (Div. 1)","handle": "adedalic","newRating": 2213,"oldRating": 2269,"rank": 268,"ratingUpdateTimeSeconds": 1530461100},{"contestId": 1007,"contestName": "Codeforces Round #497 (Div. 1)","handle": "adedalic","newRating": 2301,"oldRating": 2213,"rank": 64,"ratingUpdateTimeSeconds": 1531500300},{"contestId": 1010,"contestName": "Codeforces Round #499 (Div. 1)","handle": "adedalic","newRating": 2267,"oldRating": 2301,"rank": 232,"ratingUpdateTimeSeconds": 1532624700},{"contestId": 1012,"contestName": "Codeforces Round #500 (Div. 1) [based on EJOI]","handle": "adedalic","newRating": 2238,"oldRating": 2267,"rank": 192,"ratingUpdateTimeSeconds": 1532947500},{"contestId": 951,"contestName": "VK Cup 2018 - Final","handle": "adedalic","newRating": 2179,"oldRating": 2238,"rank": 18,"ratingUpdateTimeSeconds": 1534070400},{"contestId": 1037,"contestName": "Manthan, Codefest 18 (rated, Div. 1 + Div. 2)","handle": "adedalic","newRating": 2251,"oldRating": 2179,"rank": 104,"ratingUpdateTimeSeconds": 1535906100},{"contestId": 1074,"contestName": "Lyft Level 5 Challenge 2018 - Final Round (Open Div. 1)","handle": "adedalic","newRating": 2242,"oldRating": 2251,"rank": 118,"ratingUpdateTimeSeconds": 1541364000},{"contestId": 1055,"contestName": "Mail.Ru Cup 2018 Round 2","handle": "adedalic","newRating": 2344,"oldRating": 2242,"rank": 56,"ratingUpdateTimeSeconds": 1541869500},{"contestId": 1056,"contestName": "Mail.Ru Cup 2018 Round 3","handle": "adedalic","newRating": 2304,"oldRating": 2344,"rank": 253,"ratingUpdateTimeSeconds": 1543172700},{"contestId": 1091,"contestName": "Good Bye 2018","handle": "adedalic","newRating": 2365,"oldRating": 2304,"rank": 149,"ratingUpdateTimeSeconds": 1546190100},{"contestId": 1098,"contestName": "Codeforces Round #530 (Div. 1)","handle": "adedalic","newRating": 2319,"oldRating": 2365,"rank": 237,"ratingUpdateTimeSeconds": 1546715100},{"contestId": 1146,"contestName": "Forethought Future Cup - Elimination Round","handle": "adedalic","newRating": 2339,"oldRating": 2319,"rank": 128,"ratingUpdateTimeSeconds": 1555792500},{"contestId": 1149,"contestName": "Codeforces Round #556 (Div. 1)","handle": "adedalic","newRating": 2329,"oldRating": 2339,"rank": 203,"ratingUpdateTimeSeconds": 1556555700},{"contestId": 1172,"contestName": "Codeforces Round #564 (Div. 1)","handle": "adedalic","newRating": 2316,"oldRating": 2329,"rank": 177,"ratingUpdateTimeSeconds": 1559916300}],"status": "OK"}