{"result": [{"contestId": 1257,"contestName": "Educational Codeforces Round 76 (Rated for Div. 2)","handle": "keep__calm","newRating": 1715,"oldRating": 1500,"rank": 130,"ratingUpdateTimeSeconds": 1573662900},{"contestId": 1253,"contestName": "Codeforces Round #600 (Div. 2)","handle": "keep__calm","newRating": 1844,"oldRating": 1715,"rank": 172,"ratingUpdateTimeSeconds": 1573922100},{"contestId": 1263,"contestName": "Codeforces Round #603 (Div. 2)","handle": "keep__calm","newRating": 2019,"oldRating": 1844,"rank": 33,"ratingUpdateTimeSeconds": 1575045300}],"status": "OK"}