{"result": [{"contestId": 1080,"contestName": "Codeforces Round #524 (Div. 2)","handle": "Modem_","newRating": 1497,"oldRating": 1500,"rank": 1396,"ratingUpdateTimeSeconds": 1543053000},{"contestId": 1097,"contestName": "Hello 2019","handle": "Modem_","newRating": 1564,"oldRating": 1497,"rank": 1698,"ratingUpdateTimeSeconds": 1546623900},{"contestId": 1181,"contestName": "Codeforces Round #567 (Div. 2)","handle": "Modem_","newRating": 1619,"oldRating": 1564,"rank": 763,"ratingUpdateTimeSeconds": 1560684900},{"contestId": 1200,"contestName": "Codeforces Round #578 (Div. 2)","handle": "Modem_","newRating": 1674,"oldRating": 1619,"rank": 904,"ratingUpdateTimeSeconds": 1565534100},{"contestId": 1206,"contestName": "Codeforces Round #580 (Div. 2)","handle": "Modem_","newRating": 1779,"oldRating": 1674,"rank": 213,"ratingUpdateTimeSeconds": 1566143700},{"contestId": 1208,"contestName": "Manthan, Codefest 19 (open for everyone, rated, Div. 1 + Div. 2)","handle": "Modem_","newRating": 1805,"oldRating": 1779,"rank": 1092,"ratingUpdateTimeSeconds": 1566751200},{"contestId": 1215,"contestName": "Codeforces Round #585 (Div. 2)","handle": "Modem_","newRating": 1839,"oldRating": 1805,"rank": 453,"ratingUpdateTimeSeconds": 1568550900},{"contestId": 1245,"contestName": "Codeforces Round #597 (Div. 2)","handle": "Modem_","newRating": 1927,"oldRating": 1839,"rank": 189,"ratingUpdateTimeSeconds": 1572626100}],"status": "OK"}