{"result": [{"contestId": 832,"contestName": "Codeforces Round #425 (Div. 2)","handle": "szcoder","newRating": 1626,"oldRating": 1500,"rank": 291,"ratingUpdateTimeSeconds": 1500914100},{"contestId": 834,"contestName": "Codeforces Round #426 (Div. 2)","handle": "szcoder","newRating": 1801,"oldRating": 1626,"rank": 52,"ratingUpdateTimeSeconds": 1501432500},{"contestId": 835,"contestName": "Codeforces Round #427 (Div. 2)","handle": "szcoder","newRating": 1824,"oldRating": 1801,"rank": 315,"ratingUpdateTimeSeconds": 1501518900},{"contestId": 841,"contestName": "Codeforces Round #429 (Div. 2)","handle": "szcoder","newRating": 1892,"oldRating": 1824,"rank": 119,"ratingUpdateTimeSeconds": 1503075900},{"contestId": 844,"contestName": "AIM Tech Round 4 (Div. 2)","handle": "szcoder","newRating": 1722,"oldRating": 1892,"rank": 2920,"ratingUpdateTimeSeconds": 1503601500},{"contestId": 842,"contestName": "Codeforces Round #430 (Div. 2)","handle": "szcoder","newRating": 1877,"oldRating": 1722,"rank": 44,"ratingUpdateTimeSeconds": 1504026300},{"contestId": 849,"contestName": "Codeforces Round #431 (Div. 2)","handle": "szcoder","newRating": 1904,"oldRating": 1877,"rank": 189,"ratingUpdateTimeSeconds": 1504280100},{"contestId": 859,"contestName": "MemSQL Start[c]UP 3.0 - Round 1","handle": "szcoder","newRating": 1888,"oldRating": 1904,"rank": 580,"ratingUpdateTimeSeconds": 1505592300},{"contestId": 867,"contestName": "Codeforces Round #437 (Div. 2, based on MemSQL Start[c]UP 3.0 - Round 2)","handle": "szcoder","newRating": 1858,"oldRating": 1888,"rank": 295,"ratingUpdateTimeSeconds": 1506801900},{"contestId": 869,"contestName": "Codeforces Round #439 (Div. 2)","handle": "szcoder","newRating": 1915,"oldRating": 1858,"rank": 110,"ratingUpdateTimeSeconds": 1507304100},{"contestId": 891,"contestName": "Codeforces Round #446 (Div. 1)","handle": "szcoder","newRating": 1917,"oldRating": 1915,"rank": 294,"ratingUpdateTimeSeconds": 1510936500},{"contestId": 906,"contestName": "Codeforces Round #454 (Div. 1, based on Technocup 2018 Elimination Round 4)","handle": "szcoder","newRating": 2032,"oldRating": 1917,"rank": 129,"ratingUpdateTimeSeconds": 1514045100},{"contestId": 956,"contestName": "Codeforces Round #472 (rated, Div. 1, based on VK Cup 2018 Round 2)","handle": "szcoder","newRating": 2053,"oldRating": 2032,"rank": 168,"ratingUpdateTimeSeconds": 1521913800}],"status": "OK"}